XStatic_DataTables-1.10.15.1-py3.13-nspkg.pth
xstatic/pkg/datatables/__init__.py
xstatic/pkg/datatables/data/css/dataTables.bootstrap.css
xstatic/pkg/datatables/data/css/dataTables.bootstrap.min.css
xstatic/pkg/datatables/data/css/dataTables.bootstrap4.css
xstatic/pkg/datatables/data/css/dataTables.bootstrap4.min.css
xstatic/pkg/datatables/data/css/dataTables.foundation.css
xstatic/pkg/datatables/data/css/dataTables.foundation.min.css
xstatic/pkg/datatables/data/css/dataTables.jqueryui.css
xstatic/pkg/datatables/data/css/dataTables.jqueryui.min.css
xstatic/pkg/datatables/data/css/dataTables.material.css
xstatic/pkg/datatables/data/css/dataTables.material.min.css
xstatic/pkg/datatables/data/css/dataTables.semanticui.css
xstatic/pkg/datatables/data/css/dataTables.semanticui.min.css
xstatic/pkg/datatables/data/css/dataTables.uikit.css
xstatic/pkg/datatables/data/css/dataTables.uikit.min.css
xstatic/pkg/datatables/data/css/jquery.dataTables.css
xstatic/pkg/datatables/data/css/jquery.dataTables.min.css
xstatic/pkg/datatables/data/css/jquery.dataTables_themeroller.css
xstatic/pkg/datatables/data/images/Sorting icons.psd
xstatic/pkg/datatables/data/images/favicon.ico
xstatic/pkg/datatables/data/images/sort_asc.png
xstatic/pkg/datatables/data/images/sort_asc_disabled.png
xstatic/pkg/datatables/data/images/sort_both.png
xstatic/pkg/datatables/data/images/sort_desc.png
xstatic/pkg/datatables/data/images/sort_desc_disabled.png
xstatic/pkg/datatables/data/js/dataTables.bootstrap.js
xstatic/pkg/datatables/data/js/dataTables.bootstrap.min.js
xstatic/pkg/datatables/data/js/dataTables.bootstrap4.js
xstatic/pkg/datatables/data/js/dataTables.bootstrap4.min.js
xstatic/pkg/datatables/data/js/dataTables.foundation.js
xstatic/pkg/datatables/data/js/dataTables.foundation.min.js
xstatic/pkg/datatables/data/js/dataTables.jqueryui.js
xstatic/pkg/datatables/data/js/dataTables.jqueryui.min.js
xstatic/pkg/datatables/data/js/dataTables.material.js
xstatic_datatables-1.10.15.1.dist-info/METADATA
xstatic_datatables-1.10.15.1.dist-info/WHEEL
xstatic_datatables-1.10.15.1.dist-info/namespace_packages.txt
xstatic_datatables-1.10.15.1.dist-info/top_level.txt
xstatic_datatables-1.10.15.1.dist-info/RECORD
