Metadata-Version: 2.4
Name: XStatic-DataTables
Version: 1.10.15.1
Summary: DataTables 1.10.15 (XStatic packaging standard)
Home-page: http://www.datatables.net
Maintainer: David Moreau Simard
Maintainer-email: dmsimard@redhat.com
License: (same as DataTables)
Keywords: datatables xstatic
Platform: any
Dynamic: description
Dynamic: home-page
Dynamic: keywords
Dynamic: license
Dynamic: maintainer
Dynamic: maintainer-email
Dynamic: platform
Dynamic: summary
